[
  {
    "id": "s90-p1",
    "italian": "Quando è stato fondato questo paese?",
    "english": "When was this town founded?",
    "type": "phrase",
    "choicesItalian": [
      "Quando è stato fondato questo paese?",
      "Dov'è il castello sulla collina?",
      "C'è una guida per il museo?",
      "Quanto costa il biglietto?"
    ],
    "choicesEnglish": [
      "When was this town founded?",
      "Where is the castle on the hill?",
      "Is there a guide for the museum?",
      "How much is the ticket?"
    ],
    "correctAnswerItalian": "Quando è stato fondato questo paese?",
    "correctAnswerEnglish": "When was this town founded?",
    "feedback": {
      "correctItalian": "Ottimo! Una domanda classica sulle origini di un luogo.",
      "incorrectItalian": "No, stai chiedendo la data di fondazione del paese.",
      "correctEnglish": "Great! A classic question about the origins of a place.",
      "incorrectEnglish": "No, you are asking for the town's founding date."
    },
    "audio": {
      "italian": "/audio/e3fb6c6a484e.opus"
    }
  },
  {
    "id": "s90-p2",
    "italian": "È stato fondato dai Romani.",
    "english": "It was founded by the Romans.",
    "type": "phrase",
    "choicesItalian": [
      "È stato fondato dai Romani.",
      "È stato costruito nel Medioevo.",
      "È stato distrutto dalla peste.",
      "È stato restaurato ieri."
    ],
    "choicesEnglish": [
      "It was founded by the Romans.",
      "It was built in the Middle Ages.",
      "It was destroyed by the plague.",
      "It was restored yesterday."
    ],
    "correctAnswerItalian": "È stato fondato dai Romani.",
    "correctAnswerEnglish": "It was founded by the Romans.",
    "feedback": {
      "correctItalian": "Esatto! Molte città italiane hanno questa origine.",
      "incorrectItalian": "No, si riferisce alla fondazione romana.",
      "correctEnglish": "Exactly! Many Italian cities have this origin.",
      "incorrectEnglish": "No, it refers to the Roman foundation."
    },
    "audio": {
      "italian": "/audio/a787f64ddea0.opus"
    }
  },
  {
    "id": "s90-p3",
    "italian": "Qual è questo monumento?",
    "english": "What is this monument?",
    "type": "phrase",
    "choicesItalian": [
      "Qual è questo monumento?",
      "Chi è questa persona?",
      "Dove si trova il palazzo?",
      "Quando apre il giardino?"
    ],
    "choicesEnglish": [
      "What is this monument?",
      "Who is this person?",
      "Where is the palace located?",
      "When does the garden open?"
    ],
    "correctAnswerItalian": "Qual è questo monumento?",
    "correctAnswerEnglish": "What is this monument?",
    "feedback": {
      "correctItalian": "Giusto! Per chiedere il nome o la funzione di un'opera.",
      "incorrectItalian": "No, vuoi identificare l'opera storica davanti a te.",
      "correctEnglish": "Right! To ask the name or function of a work.",
      "incorrectEnglish": "No, you want to identify the historical work in front of you."
    },
    "audio": {
      "italian": "/audio/9dc601e6a9f6.opus"
    }
  },
  {
    "id": "s90-p4",
    "italian": "Risale al Medioevo.",
    "english": "It dates back to the Middle Ages.",
    "type": "phrase",
    "choicesItalian": [
      "Risale al Medioevo.",
      "Viene dal Rinascimento.",
      "È dell'epoca romana.",
      "È un palazzo moderno."
    ],
    "choicesEnglish": [
      "It dates back to the Middle Ages.",
      "It comes from the Renaissance.",
      "It's from the Roman era.",
      "It's a modern building."
    ],
    "correctAnswerItalian": "Risale al Medioevo.",
    "correctAnswerEnglish": "It dates back to the Middle Ages.",
    "feedback": {
      "correctItalian": "Ottimo! Identificare l'epoca medievale.",
      "incorrectItalian": "No, indica che la costruzione è dei secoli tra il V e il XV.",
      "correctEnglish": "Great! Identifying the medieval era.",
      "incorrectEnglish": "No, it indicates the construction is from the 5th to 15th centuries."
    },
    "audio": {
      "italian": "/audio/31d4a6ee066d.opus"
    }
  },
  {
    "id": "s90-p5",
    "italian": "Questa villa apparteneva a una famiglia nobile.",
    "english": "This villa belonged to a noble family.",
    "type": "phrase",
    "choicesItalian": [
      "Questa villa apparteneva a una famiglia nobile.",
      "Questo bar apparteneva a un vecchio amico.",
      "Questa casa apparteneva a un pittore famoso.",
      "Questo giardino apparteneva al comune."
    ],
    "choicesEnglish": [
      "This villa belonged to a noble family.",
      "This bar belonged to an old friend.",
      "This house belonged to a famous painter.",
      "This garden belonged to the municipality."
    ],
    "correctAnswerItalian": "Questa villa apparteneva a una famiglia nobile.",
    "correctAnswerEnglish": "This villa belonged to a noble family.",
    "feedback": {
      "correctItalian": "Esatto! Una spiegazione tipica per gli edifici storici.",
      "incorrectItalian": "No, parla del passato proprietario aristocratico.",
      "correctEnglish": "Exactly! A typical explanation for historical buildings.",
      "incorrectEnglish": "No, it speaks of the past aristocratic owner."
    },
    "audio": {
      "italian": "/audio/0fbabefc89e5.opus"
    }
  },
  {
    "id": "s90-p6",
    "italian": "C'è una famosa leggenda.",
    "english": "There is a famous legend.",
    "type": "phrase",
    "choicesItalian": [
      "C'è una famosa leggenda.",
      "C'è una brutta notizia.",
      "C'è una nuova legge.",
      "C'è una festa stasera."
    ],
    "choicesEnglish": [
      "There is a famous legend.",
      "There is some bad news.",
      "There is a new law.",
      "There is a party tonight."
    ],
    "correctAnswerItalian": "C'è una famosa leggenda.",
    "correctAnswerEnglish": "There is a famous legend.",
    "feedback": {
      "correctItalian": "Giusto! Per introdurre un racconto tradizionale.",
      "incorrectItalian": "No, stai parlando di una storia popolare nota.",
      "correctEnglish": "Right! To introduce a traditional story.",
      "incorrectEnglish": "No, you are talking about a well-known folk story."
    },
    "audio": {
      "italian": "/audio/f1c0a17e7c6f.opus"
    }
  },
  {
    "id": "s90-p7",
    "italian": "È una vecchia leggenda.",
    "english": "It's an old legend.",
    "type": "phrase",
    "choicesItalian": [
      "È una vecchia leggenda.",
      "È una storia vera.",
      "È un fatto recente.",
      "È una bugia divertente."
    ],
    "choicesEnglish": [
      "It's an old legend.",
      "It's a true story.",
      "It's a recent fact.",
      "It's a funny lie."
    ],
    "correctAnswerItalian": "È una vecchia leggenda.",
    "correctAnswerEnglish": "It's an old legend.",
    "feedback": {
      "correctItalian": "Ottimo! Confermare che il racconto è antico.",
      "incorrectItalian": "No, descrive l'anzianità della storia.",
      "correctEnglish": "Great! Confirming the story is ancient.",
      "incorrectEnglish": "No, it describes the age of the story."
    },
    "audio": {
      "italian": "/audio/dde69b564e9f.opus"
    }
  },
  {
    "id": "s90-p8",
    "italian": "Il monumento si trova nel quartiere antico.",
    "english": "The monument is located in the old quarter.",
    "type": "phrase",
    "choicesItalian": [
      "Il monumento si trova nel quartiere antico.",
      "Il castello si trova sulla collina alta.",
      "La guida si trova dentro il museo.",
      "La targa si trova dietro la statua."
    ],
    "choicesEnglish": [
      "The monument is located in the old quarter.",
      "The castle is located on the high hill.",
      "The guide is located inside the museum.",
      "The plaque is located behind the statue."
    ],
    "correctAnswerItalian": "Il monumento si trova nel quartiere antico.",
    "correctAnswerEnglish": "The monument is located in the old quarter.",
    "feedback": {
      "correctItalian": "Esatto! Una localizzazione spaziale utile.",
      "incorrectItalian": "No, stai indicando la zona storica della città.",
      "correctEnglish": "Exactly! A useful spatial localization.",
      "incorrectEnglish": "No, you are indicating the historical area of the city."
    },
    "audio": {
      "italian": "/audio/0223b38996a2.opus"
    }
  },
  {
    "id": "s90-p9",
    "italian": "Molti palazzi del centro risalgono al Medioevo.",
    "english": "Many buildings in the center date back to the Middle Ages.",
    "type": "phrase",
    "choicesItalian": [
      "Molti palazzi del centro risalgono al Medioevo.",
      "Poche case della piazza sono romane.",
      "Tutti i negozi della via sono nuovi.",
      "Alcuni giardini del borgo sono privati."
    ],
    "choicesEnglish": [
      "Many buildings in the center date back to the Middle Ages.",
      "Few houses in the square are Roman.",
      "All shops on the street are new.",
      "Some gardens in the village are private."
    ],
    "correctAnswerItalian": "Molti palazzi del centro risalgono al Medioevo.",
    "correctAnswerEnglish": "Many buildings in the center date back to the Middle Ages.",
    "feedback": {
      "correctItalian": "Giusto! Descrivere l'architettura prevalente del centro storico.",
      "incorrectItalian": "No, parla dell'origine medievale di numerosi edifici.",
      "correctEnglish": "Right! Describing the prevalent architecture of the historic center.",
      "incorrectEnglish": "No, it speaks of the medieval origin of numerous buildings."
    },
    "audio": {
      "italian": "/audio/eb70ac9126c5.opus"
    }
  },
  {
    "id": "s90-p10",
    "italian": "È un racconto interessante.",
    "english": "It's an interesting story.",
    "type": "phrase",
    "choicesItalian": [
      "È un racconto interessante.",
      "È un libro noioso.",
      "È un film lungo.",
      "È un gioco difficile."
    ],
    "choicesEnglish": [
      "It's an interesting story.",
      "It's a boring book.",
      "It's a long movie.",
      "It's a difficult game."
    ],
    "correctAnswerItalian": "È un racconto interessante.",
    "correctAnswerEnglish": "It's an interesting story.",
    "feedback": {
      "correctItalian": "Ottimo! Esprimere apprezzamento per la storia ascoltata.",
      "incorrectItalian": "No, stai lodando la narrazione.",
      "correctEnglish": "Great! Expressing appreciation for the story heard.",
      "incorrectEnglish": "No, you are praising the narrative."
    },
    "audio": {
      "italian": "/audio/b08f4146f548.opus"
    }
  },
  {
    "id": "s90-p11",
    "italian": "Il giardino è pubblico.",
    "english": "The garden is public.",
    "type": "phrase",
    "choicesItalian": [
      "Il giardino è pubblico.",
      "Il palazzo è chiuso.",
      "Il museo è caro.",
      "Il tour è gratuito."
    ],
    "choicesEnglish": [
      "The garden is public.",
      "The palace is closed.",
      "The museum is expensive.",
      "The tour is free."
    ],
    "correctAnswerItalian": "Il giardino è pubblico.",
    "correctAnswerEnglish": "The garden is public.",
    "feedback": {
      "correctItalian": "Esatto! Significa che tutti possono entrarci.",
      "incorrectItalian": "No, indica l'accessibilità libera del parco.",
      "correctEnglish": "Exactly! It means everyone can enter it.",
      "incorrectEnglish": "No, it indicates the free accessibility of the park."
    },
    "audio": {
      "italian": "/audio/3ee017ad7dbb.opus"
    }
  },
  {
    "id": "s90-p12",
    "italian": "C'è una guida che spiega la storia?",
    "english": "Is there a guide who explains the history?",
    "type": "phrase",
    "choicesItalian": [
      "C'è una guida che spiega la storia?",
      "C'è un bar che vende il vino?",
      "C'è un bus che porta alla torre?",
      "C'è una targa che dice il nome?"
    ],
    "choicesEnglish": [
      "Is there a guide who explains the history?",
      "Is there a bar that sells wine?",
      "Is there a bus that goes to the tower?",
      "Is there a plaque that says the name?"
    ],
    "correctAnswerItalian": "C'è una guida che spiega la storia?",
    "correctAnswerEnglish": "Is there a guide who explains the history?",
    "feedback": {
      "correctItalian": "Giusto! Chiedere assistenza professionale per la visita.",
      "incorrectItalian": "No, cerchi qualcuno che ti racconti il passato del luogo.",
      "correctEnglish": "Right! Asking for professional assistance for the visit.",
      "incorrectEnglish": "No, you are looking for someone to tell you the place's past."
    },
    "audio": {
      "italian": "/audio/16f164e5b5ba.opus"
    }
  },
  {
    "id": "s90-p13",
    "italian": "Questa è una copia, l'originale è nel museo.",
    "english": "This is a copy, the original is in the museum.",
    "type": "phrase",
    "choicesItalian": [
      "Questa è una copia, l'originale è nel museo.",
      "Questo è un palazzo, la villa è sulla collina.",
      "Questa è una statua, il quadro è nella chiesa.",
      "Questa è una targa, il libro è alla cassa."
    ],
    "choicesEnglish": [
      "This is a copy, the original is in the museum.",
      "This is a palace, the villa is on the hill.",
      "This is a statue, the painting is in the church.",
      "This is a plaque, the book is at the desk."
    ],
    "correctAnswerItalian": "Questa è una copia, l'originale è nel museo.",
    "correctAnswerEnglish": "This is a copy, the original is in the museum.",
    "feedback": {
      "correctItalian": "Esatto! Per non confondere la riproduzione con l'opera vera.",
      "incorrectItalian": "No, specifica che l'opera originale è conservata altrove.",
      "correctEnglish": "Exactly! Not to confuse the reproduction with the real work.",
      "incorrectEnglish": "No, it specifies that the original work is kept elsewhere."
    },
    "audio": {
      "italian": "/audio/a1febaa5ab1f.opus"
    }
  },
  {
    "id": "s90-p14",
    "italian": "C'è una targa che lo spiega?",
    "english": "Is there a plaque that explains it?",
    "type": "phrase",
    "choicesItalian": [
      "C'è una targa che lo spiega?",
      "C'è un amico che lo sa?",
      "C'è un libro che lo dice?",
      "C'è una foto che lo mostra?"
    ],
    "choicesEnglish": [
      "Is there a plaque that explains it?",
      "Is there a friend who knows it?",
      "Is there a book that says it?",
      "Is there a photo that shows it?"
    ],
    "correctAnswerItalian": "C'è una targa che lo spiega?",
    "correctAnswerEnglish": "Is there a plaque that explains it?",
    "feedback": {
      "correctItalian": "Ottimo! Cercare informazioni scritte sul monumento.",
      "incorrectItalian": "No, stai chiedendo se ci sono iscrizioni esplicative.",
      "correctEnglish": "Great! Looking for written information on the monument.",
      "incorrectEnglish": "No, you are asking if there are explanatory inscriptions."
    },
    "audio": {
      "italian": "/audio/a642688a3021.opus"
    }
  },
  {
    "id": "s90-p15",
    "italian": "È un'occasione unica.",
    "english": "It's a unique opportunity.",
    "type": "phrase",
    "choicesItalian": [
      "È un'occasione unica.",
      "È un problema grande.",
      "È una gita noiosa.",
      "È una cosa normale."
    ],
    "choicesEnglish": [
      "It's a unique opportunity.",
      "It's a big problem.",
      "It's a boring trip.",
      "It's a normal thing."
    ],
    "correctAnswerItalian": "È un'occasione unica.",
    "correctAnswerEnglish": "It's a unique opportunity.",
    "feedback": {
      "correctItalian": "Giusto! Per descrivere un evento raro o speciale.",
      "incorrectItalian": "No, sottolinea l'eccezionalità del momento.",
      "correctEnglish": "Right! To describe a rare or special event.",
      "incorrectEnglish": "No, it emphasizes the exceptional nature of the moment."
    },
    "audio": {
      "italian": "/audio/beb423dd7316.opus"
    }
  },
  {
    "id": "s90-p16",
    "italian": "Guardi gli affreschi originali.",
    "english": "Look at the original frescoes.",
    "type": "phrase",
    "choicesItalian": [
      "Guardi gli affreschi originali.",
      "Mangi i dolci tipici.",
      "Beva il vino rosso.",
      "Compri le foto nuove."
    ],
    "choicesEnglish": [
      "Look at the original frescoes.",
      "Eat the typical sweets.",
      "Drink the red wine.",
      "Buy the new photos."
    ],
    "correctAnswerItalian": "Guardi gli affreschi originali.",
    "correctAnswerEnglish": "Look at the original frescoes.",
    "feedback": {
      "correctItalian": "Esatto! Un invito ad ammirare le pitture murali vere.",
      "incorrectItalian": "No, stai suggerendo di osservare le decorazioni antiche.",
      "correctEnglish": "Exactly! An invitation to admire the real wall paintings.",
      "incorrectEnglish": "No, you are suggesting observing the ancient decorations."
    },
    "audio": {
      "italian": "/audio/be338ea86b1b.opus"
    }
  },
  {
    "id": "s90-p17",
    "italian": "Vede quella casa con lo stemma?",
    "english": "Do you see that house with the coat of arms?",
    "type": "phrase",
    "choicesItalian": [
      "Vede quella casa con lo stemma?",
      "Cerca quella via con la targa?",
      "Chiama quella donna con la guida?",
      "Paga quella birra con la moneta?"
    ],
    "choicesEnglish": [
      "Do you see that house with the coat of arms?",
      "Are you looking for that street with the plaque?",
      "Are you calling that woman with the guide?",
      "Are you paying for that beer with the coin?"
    ],
    "correctAnswerItalian": "Vede quella casa con lo stemma?",
    "correctAnswerEnglish": "Do you see that house with the coat of arms?",
    "feedback": {
      "correctItalian": "Ottimo! Per attirare l'attenzione su un dettaglio nobiliare.",
      "incorrectItalian": "No, stai indicando un edificio specifico con un emblema.",
      "correctEnglish": "Great! To draw attention to a noble detail.",
      "incorrectEnglish": "No, you are pointing out a specific building with an emblem."
    },
    "audio": {
      "italian": "/audio/10e334369a54.opus"
    }
  },
  {
    "id": "s90-p18",
    "italian": "I Malatesta erano i signori della città.",
    "english": "The Malatesta were the lords of the city.",
    "type": "phrase",
    "choicesItalian": [
      "I Malatesta erano i signori della città.",
      "I Romani erano gli schiavi del borgo.",
      "I turisti erano i nemici del museo.",
      "I bambini erano i custodi del parco."
    ],
    "choicesEnglish": [
      "The Malatesta were the lords of the city.",
      "The Romans were the slaves of the village.",
      "The tourists were the enemies of the museum.",
      "The children were the custodians of the park."
    ],
    "correctAnswerItalian": "I Malatesta erano i signori della città.",
    "correctAnswerEnglish": "The Malatesta were the lords of the city.",
    "feedback": {
      "correctItalian": "Giusto! Informazione sulla famiglia dominante del passato.",
      "incorrectItalian": "No, parla del potere storico della famiglia Malatesta.",
      "correctEnglish": "Right! Information on the dominant family of the past.",
      "incorrectEnglish": "No, it speaks of the historical power of the Malatesta family."
    },
    "audio": {
      "italian": "/audio/4715126f4599.opus"
    }
  },
  {
    "id": "s90-p19",
    "italian": "Dentro ci sono affreschi bellissimi.",
    "english": "Inside there are beautiful frescoes.",
    "type": "phrase",
    "choicesItalian": [
      "Dentro ci sono affreschi bellissimi.",
      "Fuori ci sono rumori fastidiosi.",
      "Sotto ci sono pietre pesanti.",
      "Sopra ci sono tetti rotti."
    ],
    "choicesEnglish": [
      "Inside there are beautiful frescoes.",
      "Outside there are annoying noises.",
      "Underneath there are heavy stones.",
      "Above there are broken roofs."
    ],
    "correctAnswerItalian": "Dentro ci sono affreschi bellissimi.",
    "correctAnswerEnglish": "Inside there are beautiful frescoes.",
    "feedback": {
      "correctItalian": "Esatto! Una descrizione positiva degli interni.",
      "incorrectItalian": "No, parla delle decorazioni pittoriche interne.",
      "correctEnglish": "Exactly! A positive description of the interiors.",
      "incorrectEnglish": "No, it speaks of the internal pictorial decorations."
    },
    "audio": {
      "italian": "/audio/f60652c58872.opus"
    }
  },
  {
    "id": "s90-p20",
    "italian": "È un racconto molto affascinante.",
    "english": "It is a very fascinating story.",
    "type": "phrase",
    "choicesItalian": [
      "È un racconto molto affascinante.",
      "È un libro molto noioso.",
      "È un fatto molto triste.",
      "È un gioco molto facile."
    ],
    "choicesEnglish": [
      "It is a very fascinating story.",
      "It is a very boring book.",
      "It is a very sad fact.",
      "It is a very easy game."
    ],
    "correctAnswerItalian": "È un racconto molto affascinante.",
    "correctAnswerEnglish": "It is a very fascinating story.",
    "feedback": {
      "correctItalian": "Ottimo! Per mostrare grande interesse per la storia locale.",
      "incorrectItalian": "No, esprimi attrazione per la narrazione.",
      "correctEnglish": "Great! To show great interest in local history.",
      "incorrectEnglish": "No, you express attraction for the narrative."
    },
    "audio": {
      "italian": "/audio/c08a10cbc159.opus"
    }
  },
  {
    "id": "s90-p21",
    "italian": "Quando è stato costruito questo quartiere?",
    "english": "When was this neighborhood built?",
    "type": "phrase",
    "choicesItalian": [
      "Quando è stato costruito questo quartiere?",
      "Dove si mangia bene in piazza?",
      "Chi ha perso la borsa qui?",
      "Come si chiama la guida ora?"
    ],
    "choicesEnglish": [
      "When was this neighborhood built?",
      "Where can one eat well in the square?",
      "Who lost the bag here?",
      "What is the guide's name now?"
    ],
    "correctAnswerItalian": "Quando è stato costruito questo quartiere?",
    "correctAnswerEnglish": "When was this neighborhood built?",
    "feedback": {
      "correctItalian": "Giusto! Chiedere informazioni sull'età di una zona urbana.",
      "incorrectItalian": "No, vuoi sapere la data di costruzione del quartiere.",
      "correctEnglish": "Right! Asking for information about the age of an urban area.",
      "incorrectEnglish": "No, you want to know the neighborhood's construction date."
    },
    "audio": {
      "italian": "/audio/757b45379b2e.opus"
    }
  },
  {
    "id": "s90-p22",
    "italian": "Il monumento si trova nel quartiere antico.",
    "english": "The monument is in the old quarter.",
    "type": "phrase",
    "choicesItalian": [
      "Il monumento si trova nel quartiere antico.",
      "Il bar si trova nel centro nuovo.",
      "Il porto si trova nel mare blu.",
      "Il bosco si trova nel monte alto."
    ],
    "choicesEnglish": [
      "The monument is in the old quarter.",
      "The bar is in the new center.",
      "The port is in the blue sea.",
      "The woods are in the high mountain."
    ],
    "correctAnswerItalian": "Il monumento si trova nel quartiere antico.",
    "correctAnswerEnglish": "The monument is in the old quarter.",
    "feedback": {
      "correctItalian": "Esatto! Una precisazione geografica sulla storia locale.",
      "incorrectItalian": "No, indica la posizione precisa nel borgo storico.",
      "correctEnglish": "Exactly! A geographical specification on local history.",
      "incorrectEnglish": "No, it indicates the precise position in the historical village."
    },
    "audio": {
      "italian": "/audio/0223b38996a2.opus"
    }
  },
  {
    "id": "s90-p23",
    "italian": "C'è una famosa leggenda su questo castello.",
    "english": "There is a famous legend about this castle.",
    "type": "phrase",
    "choicesItalian": [
      "C'è una famosa leggenda su questo castello.",
      "C'è un grande mercato in questa via.",
      "C'è un nuovo museo in questo palazzo.",
      "C'è un bar aperto in questa piazza."
    ],
    "choicesEnglish": [
      "There is a famous legend about this castle.",
      "There is a big market in this street.",
      "There is a new museum in this building.",
      "There is an open bar in this square."
    ],
    "correctAnswerItalian": "C'è una famosa leggenda su questo castello.",
    "correctAnswerEnglish": "There is a famous legend about this castle.",
    "feedback": {
      "correctItalian": "Ottimo! Introdurre un elemento folcloristico legato a un edificio.",
      "incorrectItalian": "No, parli di una storia nota riguardante il maniero.",
      "correctEnglish": "Great! Introducing a folkloric element linked to a building.",
      "incorrectEnglish": "No, you're talking about a known story regarding the manor."
    },
    "audio": {
      "italian": "/audio/bc3afbf7e2c6.opus"
    }
  },
  {
    "id": "s90-p24",
    "italian": "Si dice che una principessa fu murata viva.",
    "english": "It is said that a princess was walled in alive.",
    "type": "phrase",
    "choicesItalian": [
      "Si dice che una principessa fu murata viva.",
      "Si dice che un pittore fu pagato molto.",
      "Si dice che un re fu ucciso subito.",
      "Si dice che un cane fu perso qui."
    ],
    "choicesEnglish": [
      "It is said that a princess was walled in alive.",
      "It is said that a painter was paid a lot.",
      "It is said that a king was killed immediately.",
      "It is said that a dog was lost here."
    ],
    "correctAnswerItalian": "Si dice che una principessa fu murata viva.",
    "correctAnswerEnglish": "It is said that a princess was walled in alive.",
    "feedback": {
      "correctItalian": "Giusto! Un dettaglio cruento tipico di molte leggende medievali.",
      "incorrectItalian": "No, descrive il triste destino della protagonista della storia.",
      "correctEnglish": "Right! A macabre detail typical of many medieval legends.",
      "incorrectEnglish": "No, it describes the sad fate of the story's protagonist."
    },
    "audio": {
      "italian": "/audio/b00429cdabb5.opus"
    }
  },
  {
    "id": "s90-p25",
    "italian": "È un racconto molto interessante.",
    "english": "It is a very interesting story.",
    "type": "phrase",
    "choicesItalian": [
      "È un racconto molto interessante.",
      "È un libro molto noioso.",
      "È un film molto lungo.",
      "È un gioco molto difficile."
    ],
    "choicesEnglish": [
      "It is a very interesting story.",
      "It is a very boring book.",
      "It is a very long movie.",
      "It is a very difficult game."
    ],
    "correctAnswerItalian": "È un racconto molto interessante.",
    "correctAnswerEnglish": "It is a very interesting story.",
    "feedback": {
      "correctItalian": "Esatto! Confermare l'interesse per la spiegazione ricevuta.",
      "incorrectItalian": "No, esprimi apprezzamento per la narrazione storica.",
      "correctEnglish": "Exactly! Confirming interest in the explanation received.",
      "incorrectEnglish": "No, you express appreciation for the historical narrative."
    },
    "audio": {
      "italian": "/audio/0656c24b34f2.opus"
    }
  },
  {
    "id": "s90-p26",
    "italian": "Grazie per le spiegazioni.",
    "english": "Thanks for the explanations.",
    "type": "phrase",
    "choicesItalian": [
      "Grazie per le spiegazioni.",
      "Prego per il regalo.",
      "Scusa per il ritardo.",
      "Ciao per la festa."
    ],
    "choicesEnglish": [
      "Thanks for the explanations.",
      "You're welcome for the gift.",
      "Sorry for the delay.",
      "Bye for the party."
    ],
    "correctAnswerItalian": "Grazie per le spiegazioni.",
    "correctAnswerEnglish": "Thanks for the explanations.",
    "feedback": {
      "correctItalian": "Ottimo! Ringraziare chi ha dato informazioni storiche.",
      "incorrectItalian": "No, è un ringraziamento per i dettagli ricevuti.",
      "correctEnglish": "Great! Thanking those who gave historical information.",
      "incorrectEnglish": "No, it's a thank you for the details received."
    },
    "audio": {
      "italian": "/audio/2e4daa2ed46e.opus"
    }
  },
  {
    "id": "s90-p27",
    "italian": "Questa villa apparteneva a una famiglia nobile.",
    "english": "This villa belonged to a noble family.",
    "type": "phrase",
    "choicesItalian": [
      "Questa villa apparteneva a una famiglia nobile.",
      "Questo bar apparteneva a un amico caro.",
      "Questa casa apparteneva a un vecchio saggio.",
      "Questo parco apparteneva a un re potente."
    ],
    "choicesEnglish": [
      "This villa belonged to a noble family.",
      "This bar belonged to a dear friend.",
      "This house belonged to a wise old man.",
      "This park belonged to a powerful king."
    ],
    "correctAnswerItalian": "Questa villa apparteneva a una famiglia nobile.",
    "correctAnswerEnglish": "This villa belonged to a noble family.",
    "feedback": {
      "correctItalian": "Giusto! Fornire informazioni sulla proprietà passata.",
      "incorrectItalian": "No, parla dell'origine aristocratica dell'edificio.",
      "correctEnglish": "Right! Providing information on past ownership.",
      "incorrectEnglish": "No, it speaks of the aristocratic origin of the building."
    },
    "audio": {
      "italian": "/audio/0fbabefc89e5.opus"
    }
  },
  {
    "id": "s90-p28",
    "italian": "È uno dei meglio conservati.",
    "english": "It's one of the best preserved.",
    "type": "phrase",
    "choicesItalian": [
      "È uno dei meglio conservati.",
      "È uno dei più brutti ora.",
      "È uno dei meno usati.",
      "È uno dei quasi rotti."
    ],
    "choicesEnglish": [
      "It's one of the best preserved.",
      "It's one of the ugliest now.",
      "It's one of the least used.",
      "It's one of the almost broken ones."
    ],
    "correctAnswerItalian": "È uno dei meglio conservati.",
    "correctAnswerEnglish": "It's one of the best preserved.",
    "feedback": {
      "correctItalian": "Esatto! Sottolineare l'ottimo stato di manutenzione.",
      "incorrectItalian": "No, indica che l'edificio è rimasto quasi intatto.",
      "correctEnglish": "Exactly! Emphasizing the excellent state of maintenance.",
      "incorrectEnglish": "No, it indicates that the building has remained almost intact."
    },
    "audio": {
      "italian": "/audio/896a2d1613a9.opus"
    }
  },
  {
    "id": "s90-p29",
    "italian": "Il giardino è pubblico.",
    "english": "The garden is public.",
    "type": "phrase",
    "choicesItalian": [
      "Il giardino è pubblico.",
      "Il bar è chiuso ora.",
      "Il museo è caro oggi.",
      "Il tour è finito già."
    ],
    "choicesEnglish": [
      "The garden is public.",
      "The bar is closed now.",
      "The museum is expensive today.",
      "The tour is finished already."
    ],
    "correctAnswerItalian": "Il giardino è pubblico.",
    "correctAnswerEnglish": "The garden is public.",
    "feedback": {
      "correctItalian": "Ottimo! Chiarire che lo spazio verde è accessibile a tutti.",
      "incorrectItalian": "No, indica che non è una proprietà privata chiusa.",
      "correctEnglish": "Great! Clarifying that the green space is accessible to everyone.",
      "incorrectEnglish": "No, it indicates it's not a closed private property."
    },
    "audio": {
      "italian": "/audio/3ee017ad7dbb.opus"
    }
  },
  {
    "id": "s90-p30",
    "italian": "C'è una fontana antica.",
    "english": "There is an ancient fountain.",
    "type": "phrase",
    "choicesItalian": [
      "C'è una fontana antica.",
      "C'è un pozzo nuovo.",
      "C'è un fiume sporco.",
      "C'è un mare calmo."
    ],
    "choicesEnglish": [
      "There is an ancient fountain.",
      "There is a new well.",
      "There is a dirty river.",
      "There is a calm sea."
    ],
    "correctAnswerItalian": "C'è una fontana antica.",
    "correctAnswerEnglish": "There is an ancient fountain.",
    "feedback": {
      "correctItalian": "Giusto! Notare un elemento decorativo e storico.",
      "incorrectItalian": "No, descrive la presenza di una vecchia struttura per l'acqua.",
      "correctEnglish": "Right! Noticing a decorative and historical element.",
      "incorrectEnglish": "No, it describes the presence of an old structure for water."
    },
    "audio": {
      "italian": "/audio/772fe56ed9de.opus"
    }
  },
  {
    "id": "s90-p31",
    "italian": "La targa è dietro la statua.",
    "english": "The plaque is behind the statue.",
    "type": "phrase",
    "choicesItalian": [
      "La targa è dietro la statua.",
      "Il libro è sopra il tavolo.",
      "La foto è vicino al muro.",
      "La via è sotto il ponte."
    ],
    "choicesEnglish": [
      "The plaque is behind the statue.",
      "The book is on top of the table.",
      "The photo is near the wall.",
      "The street is under the bridge."
    ],
    "correctAnswerItalian": "La targa è dietro la statua.",
    "correctAnswerEnglish": "The plaque is behind the statue.",
    "feedback": {
      "correctItalian": "Esatto! Un'indicazione per trovare informazioni scritte.",
      "incorrectItalian": "No, specifica la posizione dell'iscrizione.",
      "correctEnglish": "Exactly! An indication for finding written information.",
      "incorrectEnglish": "No, it specifies the position of the inscription."
    },
    "audio": {
      "italian": "/audio/685d55430b18.opus"
    }
  },
  {
    "id": "s90-p32",
    "italian": "È in italiano e inglese.",
    "english": "It is in Italian and English.",
    "type": "phrase",
    "choicesItalian": [
      "È in italiano e inglese.",
      "È in francese e tedesco.",
      "È in spagnolo e russo.",
      "È in greco e latino."
    ],
    "choicesEnglish": [
      "It is in Italian and English.",
      "It is in French and German.",
      "It is in Spanish and Russian.",
      "It is in Greek and Latin."
    ],
    "correctAnswerItalian": "È in italiano e inglese.",
    "correctAnswerEnglish": "It is in Italian and English.",
    "feedback": {
      "correctItalian": "Ottimo! Sottolineare il bilinguismo dell'informazione.",
      "incorrectItalian": "No, indica le due lingue presenti sulla targa.",
      "correctEnglish": "Great! Emphasizing the bilingualism of the information.",
      "incorrectEnglish": "No, it indicates the two languages present on the plaque."
    },
    "audio": {
      "italian": "/audio/f950fff7b680.opus"
    }
  },
  {
    "id": "s90-p33",
    "italian": "Vede quella casa con lo stemma?",
    "english": "Do you see that house with the coat of arms?",
    "type": "phrase",
    "choicesItalian": [
      "Vede quella casa con lo stemma?",
      "Cerca quella via con la targa?",
      "Chiama quel bar con la guida?",
      "Paga quel vino con la carta?"
    ],
    "choicesEnglish": [
      "Do you see that house with the coat of arms?",
      "Are you looking for that street with the plaque?",
      "Are you calling that bar with the guide?",
      "Are you paying for that wine with the card?"
    ],
    "correctAnswerItalian": "Vede quella casa con lo stemma?",
    "correctAnswerEnglish": "Do you see that house with the coat of arms?",
    "feedback": {
      "correctItalian": "Giusto! Per indicare un edificio nobiliare specifico.",
      "incorrectItalian": "No, stai attirando l'attenzione sul simbolo della casa.",
      "correctEnglish": "Right! To point out a specific noble building.",
      "incorrectEnglish": "No, you are drawing attention to the house's symbol."
    },
    "audio": {
      "italian": "/audio/10e334369a54.opus"
    }
  },
  {
    "id": "s90-p34",
    "italian": "Qual era il nome della famiglia?",
    "english": "What was the family's name?",
    "type": "phrase",
    "choicesItalian": [
      "Qual era il nome della famiglia?",
      "Dov'era la fine della via?",
      "Chi era il capo del bar?",
      "Quando era l'inizio della festa?"
    ],
    "choicesEnglish": [
      "What was the family's name?",
      "Where was the end of the street?",
      "Who was the head of the bar?",
      "When was the start of the party?"
    ],
    "correctAnswerItalian": "Qual era il nome della famiglia?",
    "correctAnswerEnglish": "What was the family's name?",
    "feedback": {
      "correctItalian": "Esatto! Chiedere l'identità degli antichi proprietari.",
      "incorrectItalian": "No, vuoi sapere come si chiamavano i nobili del palazzo.",
      "correctEnglish": "Exactly! Asking for the identity of the former owners.",
      "incorrectEnglish": "No, you want to know the names of the nobles from the palace."
    },
    "audio": {
      "italian": "/audio/a15155debecd.opus"
    }
  },
  {
    "id": "s90-p35",
    "italian": "Dentro ci sono affreschi antichi.",
    "english": "Inside there are ancient frescoes.",
    "type": "phrase",
    "choicesItalian": [
      "Dentro ci sono affreschi antichi.",
      "Fuori ci sono rumori moderni.",
      "Sotto ci sono pietre nuove.",
      "Sopra ci sono tetti sporchi."
    ],
    "choicesEnglish": [
      "Inside there are ancient frescoes.",
      "Outside there are modern noises.",
      "Underneath there are new stones.",
      "Above there are dirty roofs."
    ],
    "correctAnswerItalian": "Dentro ci sono affreschi antichi.",
    "correctAnswerEnglish": "Inside there are ancient frescoes.",
    "feedback": {
      "correctItalian": "Ottimo! Descrivere una ricchezza artistica interna.",
      "incorrectItalian": "No, si parla delle pitture murali del passato.",
      "correctEnglish": "Great! Describing internal artistic wealth.",
      "incorrectEnglish": "No, it's about wall paintings from the past."
    },
    "audio": {
      "italian": "/audio/97d9c99e8ee2.opus"
    }
  },
  {
    "id": "s90-p36",
    "italian": "Non sono visitabili.",
    "english": "They cannot be visited.",
    "type": "phrase",
    "choicesItalian": [
      "Non sono visitabili.",
      "Sono aperti ora.",
      "Sono facili da vedere.",
      "Sono molto vicini."
    ],
    "choicesEnglish": [
      "They cannot be visited.",
      "They are open now.",
      "They are easy to see.",
      "They are very close."
    ],
    "correctAnswerItalian": "Non sono visitabili.",
    "correctAnswerEnglish": "They cannot be visited.",
    "feedback": {
      "correctItalian": "Giusto! Un divieto di accesso per il pubblico.",
      "incorrectItalian": "No, indica che non è possibile fare una visita.",
      "correctEnglish": "Right! A prohibition of access for the public.",
      "incorrectEnglish": "No, it indicates that it's not possible to visit."
    },
    "audio": {
      "italian": "/audio/eda7c1b18f43.opus"
    }
  },
  {
    "id": "s90-p37",
    "italian": "È un racconto molto affascinante.",
    "english": "It's a very fascinating story.",
    "type": "phrase",
    "choicesItalian": [
      "È un racconto molto affascinante.",
      "È un libro molto noioso.",
      "È un fatto molto triste.",
      "È un gioco molto facile."
    ],
    "choicesEnglish": [
      "It's a very fascinating story.",
      "It's a very boring book.",
      "It's a very sad fact.",
      "It's a very easy game."
    ],
    "correctAnswerItalian": "È un racconto molto affascinante.",
    "correctAnswerEnglish": "It's a very fascinating story.",
    "feedback": {
      "correctItalian": "Esatto! Esprimere attrazione per la storia locale.",
      "incorrectItalian": "No, mostri interesse positivo per la narrazione.",
      "correctEnglish": "Exactly! Expressing attraction for local history.",
      "incorrectEnglish": "No, you show positive interest in the narrative."
    },
    "audio": {
      "italian": "/audio/c08a10cbc159.opus"
    }
  },
  {
    "id": "s90-p38",
    "italian": "Il monumento si trova nel quartiere antico.",
    "english": "The monument is in the old neighborhood.",
    "type": "phrase",
    "choicesItalian": [
      "Il monumento si trova nel quartiere antico.",
      "Il bar si trova nel porto nuovo.",
      "Il mare si trova nel monte alto.",
      "La guida si trova nel cinema chiuso."
    ],
    "choicesEnglish": [
      "The monument is in the old neighborhood.",
      "The bar is in the new port.",
      "The sea is on the high mountain.",
      "The guide is in the closed cinema."
    ],
    "correctAnswerItalian": "Il monumento si trova nel quartiere antico.",
    "correctAnswerEnglish": "The monument is in the old neighborhood.",
    "feedback": {
      "correctItalian": "Ottimo! Una specifica spaziale storica.",
      "incorrectItalian": "No, indica la zona antica dove cercare l'opera.",
      "correctEnglish": "Great! A specific historical spatial reference.",
      "incorrectEnglish": "No, it indicates the old area where to look for the work."
    },
    "audio": {
      "italian": "/audio/0223b38996a2.opus"
    }
  },
  {
    "id": "s90-p39",
    "italian": "Questo paese è stato fondato dai Romani.",
    "english": "This town was founded by the Romans.",
    "type": "phrase",
    "choicesItalian": [
      "Questo paese è stato fondato dai Romani.",
      "Questo borgo è stato costruito dai Greci.",
      "Questa città è stata distrutta dai nemici.",
      "Questo posto è stato venduto dai nobili."
    ],
    "choicesEnglish": [
      "This town was founded by the Romans.",
      "This village was built by the Greeks.",
      "This city was destroyed by the enemies.",
      "This place was sold by the nobles."
    ],
    "correctAnswerItalian": "Questo paese è stato fondato dai Romani.",
    "correctAnswerEnglish": "This town was founded by the Romans.",
    "feedback": {
      "correctItalian": "Giusto! Un'informazione fondamentale sulle origini locali.",
      "incorrectItalian": "No, parla del passato romano del luogo.",
      "correctEnglish": "Right! Fundamental information on local origins.",
      "incorrectEnglish": "No, it speaks of the Roman past of the place."
    },
    "audio": {
      "italian": "/audio/2ef637f58f4b.opus"
    }
  },
  {
    "id": "s90-p40",
    "italian": "Vale la pena visitarlo.",
    "english": "It's worth visiting.",
    "type": "phrase",
    "choicesItalian": [
      "Vale la pena visitarlo.",
      "È tempo perso guardarlo.",
      "Costa troppo entrarci.",
      "È molto sporco fuori."
    ],
    "choicesEnglish": [
      "It's worth visiting.",
      "It's a waste of time to look at it.",
      "It costs too much to enter.",
      "It's very dirty outside."
    ],
    "correctAnswerItalian": "Vale la pena visitarlo.",
    "correctAnswerEnglish": "It's worth visiting.",
    "feedback": {
      "correctItalian": "Esatto! Un consiglio positivo per un'attrazione.",
      "incorrectItalian": "No, suggerisce che l'esperienza è ripagata dal piacere.",
      "correctEnglish": "Exactly! A positive recommendation for an attraction.",
      "incorrectEnglish": "No, it suggests the experience is rewarded by pleasure."
    },
    "audio": {
      "italian": "/audio/f264bfcb1a4c.opus"
    }
  },
  {
    "id": "s90-p41",
    "italian": "C'è una sezione sulle famiglie nobili.",
    "english": "There is a section on noble families.",
    "type": "phrase",
    "choicesItalian": [
      "C'è una sezione sulle famiglie nobili.",
      "C'è un bar sulle colline alte.",
      "C'è una festa sulle barche nuove.",
      "C'è una gita sulle montagne innevate."
    ],
    "choicesEnglish": [
      "There is a section on noble families.",
      "There is a bar on the high hills.",
      "There is a party on the new boats.",
      "There is a trip on the snowy mountains."
    ],
    "correctAnswerItalian": "C'è una sezione sulle famiglie nobili.",
    "correctAnswerEnglish": "There is a section on noble families.",
    "feedback": {
      "correctItalian": "Ottimo! Descrivere una parte specifica del museo.",
      "incorrectItalian": "No, parla dell'area dedicata all'aristocrazia locale.",
      "correctEnglish": "Great! Describing a specific part of the museum.",
      "incorrectEnglish": "No, it speaks of the area dedicated to local aristocracy."
    },
    "audio": {
      "italian": "/audio/04bc45460161.opus"
    }
  },
  {
    "id": "s90-p42",
    "italian": "La colonna è romana.",
    "english": "The column is Roman.",
    "type": "phrase",
    "choicesItalian": [
      "La colonna è romana.",
      "La statua è greca.",
      "La porta è francese.",
      "La via è tedesca."
    ],
    "choicesEnglish": [
      "The column is Roman.",
      "The statue is Greek.",
      "The door is French.",
      "The street is German."
    ],
    "correctAnswerItalian": "La colonna è romana.",
    "correctAnswerEnglish": "The column is Roman.",
    "feedback": {
      "correctItalian": "Giusto! Identificare l'origine antica di un reperto.",
      "incorrectItalian": "No, specifica l'epoca dell'elemento architettonico.",
      "correctEnglish": "Right! Identifying the ancient origin of an artifact.",
      "incorrectEnglish": "No, it specifies the era of the architectural element."
    },
    "audio": {
      "italian": "/audio/73803857c225.opus"
    }
  },
  {
    "id": "s90-p43",
    "italian": "Risale al Medioevo la base.",
    "english": "The base dates back to the Middle Ages.",
    "type": "phrase",
    "choicesItalian": [
      "Risale al Medioevo la base.",
      "Risale al Rinascimento la cima.",
      "Risale al presente la fine.",
      "Risale al futuro l'inizio."
    ],
    "choicesEnglish": [
      "The base dates back to the Middle Ages.",
      "The top dates back to the Renaissance.",
      "The end dates back to the present.",
      "The start dates back to the future."
    ],
    "correctAnswerItalian": "Risale al Medioevo la base.",
    "correctAnswerEnglish": "The base dates back to the Middle Ages.",
    "feedback": {
      "correctItalian": "Esatto! Precisare l'epoca di una parte del monumento.",
      "incorrectItalian": "No, parla della parte inferiore e del suo periodo storico.",
      "correctEnglish": "Exactly! Specifying the era of a part of the monument.",
      "incorrectEnglish": "No, it speaks of the lower part and its historical period."
    },
    "audio": {
      "italian": "/audio/5d7b35300317.opus"
    }
  },
  {
    "id": "s90-p44",
    "italian": "C'è una festa ogni anno.",
    "english": "There is a festival every year.",
    "type": "phrase",
    "choicesItalian": [
      "C'è una festa ogni anno.",
      "C'è una guerra ogni secolo.",
      "C'è una pausa ogni ora.",
      "C'è una cena ogni sera."
    ],
    "choicesEnglish": [
      "There is a festival every year.",
      "There is a war every century.",
      "There is a break every hour.",
      "There is a dinner every evening."
    ],
    "correctAnswerItalian": "C'è una festa ogni anno.",
    "correctAnswerEnglish": "There is a festival every year.",
    "feedback": {
      "correctItalian": "Ottimo! Informare sulla regolarità di una celebrazione locale.",
      "incorrectItalian": "No, indica la cadenza annuale dell'evento.",
      "correctEnglish": "Great! Informing about the regularity of a local celebration.",
      "incorrectEnglish": "No, it indicates the annual frequency of the event."
    },
    "audio": {
      "italian": "/audio/d9df575dcaa2.opus"
    }
  },
  {
    "id": "s90-p45",
    "italian": "Dovremmo andare alla festa.",
    "english": "We should go to the festival.",
    "type": "phrase",
    "choicesItalian": [
      "Dovremmo andare alla festa.",
      "Dovremmo uscire dalla chiesa.",
      "Dovremmo correre verso il bar.",
      "Dovremmo dormire sulla panchina."
    ],
    "choicesEnglish": [
      "We should go to the festival.",
      "We should leave the church.",
      "We should run towards the bar.",
      "We should sleep on the bench."
    ],
    "correctAnswerItalian": "Dovremmo andare alla festa.",
    "correctAnswerEnglish": "We should go to the festival.",
    "feedback": {
      "correctItalian": "Giusto! Una proposta di attività sociale e culturale.",
      "incorrectItalian": "No, suggerisci di partecipare alla celebrazione.",
      "correctEnglish": "Right! A proposal for social and cultural activity.",
      "incorrectEnglish": "No, you suggest participating in the celebration."
    },
    "audio": {
      "italian": "/audio/c4f1faf0fddd.opus"
    }
  },
  {
    "id": "s90-p46",
    "italian": "Sì, ci andiamo insieme.",
    "english": "Yes, let's go together.",
    "type": "phrase",
    "choicesItalian": [
      "Sì, ci andiamo insieme.",
      "No, vai da solo.",
      "Forse, vediamo domani.",
      "Sempre, amo camminare."
    ],
    "choicesEnglish": [
      "Yes, let's go together.",
      "No, go alone.",
      "Maybe, we'll see tomorrow.",
      "Always, I love walking."
    ],
    "correctAnswerItalian": "Sì, ci andiamo insieme.",
    "correctAnswerEnglish": "Yes, let's go together.",
    "feedback": {
      "correctItalian": "Esatto! Accettare la proposta di compagnia.",
      "incorrectItalian": "No, confermi che farete la gita in gruppo.",
      "correctEnglish": "Exactly! Accepting the proposal of company.",
      "incorrectEnglish": "No, you confirm that you will go on the trip as a group."
    },
    "audio": {
      "italian": "/audio/55f1d797b5bd.opus"
    }
  },
  {
    "id": "s90-p47",
    "italian": "Fu costruita da una famiglia nobile.",
    "english": "It was built by a noble family.",
    "type": "phrase",
    "choicesItalian": [
      "Fu costruita da una famiglia nobile.",
      "Fu distrutta da un temporale brutto.",
      "Fu venduta da un mercante ricco.",
      "Fu regalata da un re generoso."
    ],
    "choicesEnglish": [
      "It was built by a noble family.",
      "It was destroyed by a bad storm.",
      "It was sold by a wealthy merchant.",
      "It was given as a gift by a generous king."
    ],
    "correctAnswerItalian": "Fu costruita da una famiglia nobile.",
    "correctAnswerEnglish": "It was built by a noble family.",
    "feedback": {
      "correctItalian": "Ottimo! Precisare i committenti storici dell'opera.",
      "incorrectItalian": "No, parla della realizzazione voluta dall'aristocrazia.",
      "correctEnglish": "Great! Specifying the historical patrons of the work.",
      "incorrectEnglish": "No, it speaks of the construction commissioned by the aristocracy."
    },
    "audio": {
      "italian": "/audio/1bf77463dab9.opus"
    }
  },
  {
    "id": "s90-p48",
    "italian": "Non è sempre aperta.",
    "english": "It is not always open.",
    "type": "phrase",
    "choicesItalian": [
      "Non è sempre aperta.",
      "È chiusa per sempre.",
      "È libera per tutti.",
      "È sporca fuori qui."
    ],
    "choicesEnglish": [
      "It is not always open.",
      "It is closed forever.",
      "It is free for everyone.",
      "It is dirty outside here."
    ],
    "correctAnswerItalian": "Non è sempre aperta.",
    "correctAnswerEnglish": "It is not always open.",
    "feedback": {
      "correctItalian": "Giusto! Un avvertimento sugli orari limitati.",
      "incorrectItalian": "No, indica che l'accessibilità non è garantita ogni giorno.",
      "correctEnglish": "Right! A warning about limited hours.",
      "incorrectEnglish": "No, it indicates that accessibility is not guaranteed every day."
    },
    "audio": {
      "italian": "/audio/653e4861e016.opus"
    }
  },
  {
    "id": "s90-p49",
    "italian": "Posso mostrarle l'interno.",
    "english": "I can show you the inside.",
    "type": "phrase",
    "choicesItalian": [
      "Posso mostrarle l'interno.",
      "Posso chiamare l'amico.",
      "Posso pagare il conto.",
      "Posso chiudere la porta."
    ],
    "choicesEnglish": [
      "I can show you the inside.",
      "I can call my friend.",
      "I can pay the bill.",
      "I can close the door."
    ],
    "correctAnswerItalian": "Posso mostrarle l'interno.",
    "correctAnswerEnglish": "I can show you the inside.",
    "feedback": {
      "correctItalian": "Esatto! Un'offerta di visita da parte di chi ha le chiavi.",
      "incorrectItalian": "No, ti stai proponendo come accompagnatore dentro l'edificio.",
      "correctEnglish": "Exactly! An offer of a visit from those who have the keys.",
      "incorrectEnglish": "No, you are offering to accompany someone inside the building."
    },
    "audio": {
      "italian": "/audio/0448382bf358.opus"
    }
  },
  {
    "id": "s90-p50",
    "italian": "Ecco la chiave.",
    "english": "Here is the key.",
    "type": "phrase",
    "choicesItalian": [
      "Ecco la chiave.",
      "Ecco il libro.",
      "Ecco la via.",
      "Ecco la festa."
    ],
    "choicesEnglish": [
      "Here is the key.",
      "Here is the book.",
      "Here is the street.",
      "Here is the festival."
    ],
    "correctAnswerItalian": "Ecco la chiave.",
    "correctAnswerEnglish": "Here is the key.",
    "feedback": {
      "correctItalian": "Ottimo! L'atto di consegnare lo strumento per aprire.",
      "incorrectItalian": "No, stai dando la chiave per entrare.",
      "correctEnglish": "Great! The act of handing over the tool to open.",
      "incorrectEnglish": "No, you are giving the key to enter."
    },
    "audio": {
      "italian": "/audio/6da185292ae1.opus"
    }
  },
  {
    "id": "s90-p51",
    "italian": "Guardi gli affreschi.",
    "english": "Look at the frescoes.",
    "type": "phrase",
    "choicesItalian": [
      "Guardi gli affreschi.",
      "Beva il vino rosso.",
      "Chiami il taxi nero.",
      "Compri il dolce ora."
    ],
    "choicesEnglish": [
      "Look at the frescoes.",
      "Drink the red wine.",
      "Call the black taxi.",
      "Buy the dessert now."
    ],
    "correctAnswerItalian": "Guardi gli affreschi.",
    "correctAnswerEnglish": "Look at the frescoes.",
    "feedback": {
      "correctItalian": "Giusto! Un invito ad osservare le decorazioni pittoriche.",
      "incorrectItalian": "No, suggerisci di guardare i dipinti sui muri.",
      "correctEnglish": "Right! An invitation to observe the pictorial decorations.",
      "incorrectEnglish": "No, you suggest looking at the paintings on the walls."
    },
    "audio": {
      "italian": "/audio/67275f4bb58d.opus"
    }
  },
  {
    "id": "s90-p52",
    "italian": "Sono originali.",
    "english": "They are original.",
    "type": "phrase",
    "choicesItalian": [
      "Sono originali.",
      "Sono finti ora.",
      "Sono nuovi oggi.",
      "Sono sporchi qui."
    ],
    "choicesEnglish": [
      "They are original.",
      "They are fake now.",
      "They are new today.",
      "They are dirty here."
    ],
    "correctAnswerItalian": "Sono originali.",
    "correctAnswerEnglish": "They are original.",
    "feedback": {
      "correctItalian": "Esatto! Confermare l'autenticità delle opere d'arte.",
      "incorrectItalian": "No, indica che non sono copie o riproduzioni.",
      "correctEnglish": "Exactly! Confirming the authenticity of the artworks.",
      "incorrectEnglish": "No, it indicates they are not copies or reproductions."
    },
    "audio": {
      "italian": "/audio/859be0c04efd.opus"
    }
  },
  {
    "id": "s90-p53",
    "italian": "Che meraviglia!",
    "english": "How wonderful!",
    "type": "phrase",
    "choicesItalian": [
      "Che meraviglia!",
      "Che brutta cosa!",
      "Che noia mortale!",
      "Che fretta inutile!"
    ],
    "choicesEnglish": [
      "How wonderful!",
      "What a bad thing!",
      "What a deadly bore!",
      "What useless haste!"
    ],
    "correctAnswerItalian": "Che meraviglia!",
    "correctAnswerEnglish": "How wonderful!",
    "feedback": {
      "correctItalian": "Ottimo! Esclamazione di stupore e ammirazione.",
      "incorrectItalian": "No, esprimi entusiasmo per la bellezza vista.",
      "correctEnglish": "Great! Exclamation of amazement and admiration.",
      "incorrectEnglish": "No, you express enthusiasm for the beauty seen."
    },
    "audio": {
      "italian": "/audio/396fa28a1683.opus"
    }
  },
  {
    "id": "s90-p54",
    "italian": "Grazie ancora.",
    "english": "Thanks again.",
    "type": "phrase",
    "choicesItalian": [
      "Grazie ancora.",
      "Prego subito.",
      "Scusa mai.",
      "Ciao dopo."
    ],
    "choicesEnglish": [
      "Thanks again.",
      "You're welcome immediately.",
      "Sorry never.",
      "Bye later."
    ],
    "correctAnswerItalian": "Grazie ancora.",
    "correctAnswerEnglish": "Thanks again.",
    "feedback": {
      "correctItalian": "Giusto! Un ringraziamento finale molto cortese.",
      "incorrectItalian": "No, stai ringraziando una seconda volta.",
      "correctEnglish": "Right! A very polite final thank you.",
      "incorrectEnglish": "No, you are thanking a second time."
    },
    "audio": {
      "italian": "/audio/54a5a11b3e0f.opus"
    }
  },
  {
    "id": "s90-p55",
    "italian": "Questo paese è molto bello.",
    "english": "This town is very beautiful.",
    "type": "phrase",
    "choicesItalian": [
      "Questo paese è molto bello.",
      "Questo borgo è molto sporco.",
      "Questa città è molto cara.",
      "Questo posto è molto vuoto."
    ],
    "choicesEnglish": [
      "This town is very beautiful.",
      "This village is very dirty.",
      "This city is very expensive.",
      "This place is very empty."
    ],
    "correctAnswerItalian": "Questo paese è molto bello.",
    "correctAnswerEnglish": "This town is very beautiful.",
    "feedback": {
      "correctItalian": "Esatto! Un complimento sincero al luogo che visiti.",
      "incorrectItalian": "No, esprimi apprezzamento estetico per il centro abitato.",
      "correctEnglish": "Exactly! A sincere compliment to the place you visit.",
      "incorrectEnglish": "No, you express aesthetic appreciation for the inhabited center."
    },
    "audio": {
      "italian": "/audio/7b8b2ffd4d06.opus"
    }
  },
  {
    "id": "s90-p56",
    "italian": "Scusi, stavo passeggiando.",
    "english": "Excuse me, I was walking / strolling.",
    "type": "phrase",
    "choicesItalian": [
      "Scusi, stavo passeggiando.",
      "Ciao, stavo correndo.",
      "Salve, stavo mangiando.",
      "Buongiorno, stavo dormendo."
    ],
    "choicesEnglish": [
      "Excuse me, I was walking / strolling.",
      "Hi, I was running.",
      "Hello, I was eating.",
      "Good morning, I was sleeping."
    ],
    "correctAnswerItalian": "Scusi, stavo passeggiando.",
    "correctAnswerEnglish": "Excuse me, I was walking / strolling.",
    "feedback": {
      "correctItalian": "Ottimo! Spiegare cosa stavi facendo prima di fermarti.",
      "incorrectItalian": "No, parli del tuo camminare rilassato per le vie.",
      "correctEnglish": "Great! Explaining what you were doing before stopping.",
      "incorrectEnglish": "No, you speak of your relaxed walking through the streets."
    },
    "audio": {
      "italian": "/audio/11c4b4ea3ef4.opus"
    }
  },
  {
    "id": "s90-p57",
    "italian": "Era un piccolo accampamento militare.",
    "english": "It was a small military camp.",
    "type": "phrase",
    "choicesItalian": [
      "Era un piccolo accampamento militare.",
      "Era un grande mercato pubblico.",
      "Era un nuovo teatro moderno.",
      "Era un vecchio bar chiuso."
    ],
    "choicesEnglish": [
      "It was a small military camp.",
      "It was a large public market.",
      "It was a new modern theater.",
      "It was an old closed bar."
    ],
    "correctAnswerItalian": "Era un piccolo accampamento militare.",
    "correctAnswerEnglish": "It was a small military camp.",
    "feedback": {
      "correctItalian": "Giusto! Informazione sulle origini difensive del luogo.",
      "incorrectItalian": "No, descrive la funzione originaria della fondazione.",
      "correctEnglish": "Right! Information on the defensive origins of the place.",
      "incorrectEnglish": "No, it describes the original function of the foundation."
    },
    "audio": {
      "italian": "/audio/84f3465fd0f7.opus"
    }
  },
  {
    "id": "s90-p58",
    "italian": "Miscele di epoche.",
    "english": "Mixtures of eras.",
    "type": "phrase",
    "choicesItalian": [
      "Miscele di epoche.",
      "Insieme di colori.",
      "Gruppo di persone.",
      "Pila di pietre."
    ],
    "choicesEnglish": [
      "Mixtures of eras.",
      "Set of colors.",
      "Group of people.",
      "Pile of stones."
    ],
    "correctAnswerItalian": "Miscele di epoche.",
    "correctAnswerEnglish": "Mixtures of eras.",
    "feedback": {
      "correctItalian": "Esatto! Quando stili storici diversi si sovrappongono.",
      "incorrectItalian": "No, indica la presenza di vari periodi storici nello stesso luogo.",
      "correctEnglish": "Exactly! When different historical styles overlap.",
      "incorrectEnglish": "No, it indicates the presence of various historical periods in the same place."
    },
    "audio": {
      "italian": "/audio/a77576b8c7f1.opus"
    }
  },
  {
    "id": "s90-p59",
    "italian": "Si dice che una principessa sia stata murata viva.",
    "english": "It is said that a princess was walled in alive.",
    "type": "phrase",
    "choicesItalian": [
      "Si dice che una principessa sia stata murata viva.",
      "Si dice che un re sia stato felice sempre.",
      "Si dice che un cane sia stato perso ieri.",
      "Si dice che un bar sia stato aperto ora."
    ],
    "choicesEnglish": [
      "It is said that a princess was walled in alive.",
      "It is said that a king was happy always.",
      "It is said that a dog was lost yesterday.",
      "It is said that a bar was opened now."
    ],
    "correctAnswerItalian": "Si dice che una principessa sia stata murata viva.",
    "correctAnswerEnglish": "It is said that a princess was walled in alive.",
    "feedback": {
      "correctItalian": "Ottimo! Un racconto drammatico tipico del folclore.",
      "incorrectItalian": "No, riporta una voce popolare su un evento tragico.",
      "correctEnglish": "Great! A dramatic tale typical of folklore.",
      "incorrectEnglish": "No, it reports a popular rumor about a tragic event."
    },
    "audio": {
      "italian": "/audio/ad38c223a633.opus"
    }
  },
  {
    "id": "s90-p60",
    "italian": "Buona visita.",
    "english": "Enjoy your visit.",
    "type": "phrase",
    "choicesItalian": [
      "Buona visita.",
      "Buona notte.",
      "Buon viaggio.",
      "Buon appetito."
    ],
    "choicesEnglish": [
      "Enjoy your visit.",
      "Good night.",
      "Have a good trip.",
      "Enjoy your meal."
    ],
    "correctAnswerItalian": "Buona visita.",
    "correctAnswerEnglish": "Enjoy your visit.",
    "feedback": {
      "correctItalian": "Giusto! Un augurio cortese per chi inizia un tour.",
      "incorrectItalian": "No, è un saluto per chi va a vedere dei monumenti.",
      "correctEnglish": "Right! A polite wish for those starting a tour.",
      "incorrectEnglish": "No, it's a greeting for those going to see monuments."
    },
    "audio": {
      "italian": "/audio/d63af6ab1564.opus"
    }
  }
]